toldwords/__init__.py
toldwords/openai.py
toldwords/pretalx.py
toldwords/py.typed
toldwords/utils.py
toldwords-1.0.0.dist-info/LICENSE.txt
toldwords-1.0.0.dist-info/METADATA
toldwords-1.0.0.dist-info/WHEEL
toldwords-1.0.0.dist-info/RECORD
