Metadata-Version: 2.1
Name: toldwords
Version: 1.0.0
Summary: Using ChatGPT to make keywords for the papers from COSCUP.
Home-page: https://github.com/toomore/toldwords
License: MIT
Keywords: API,ChatGPT,pretalx,COSCUP,openai
Author: Toomore Chiang
Author-email: toomore0929@gmail.com
Requires-Python: >=3.10,<4.0
Classifier: License :: OSI Approved :: MIT License
Classifier: Natural Language :: Chinese (Traditional)
Classifier: Natural Language :: English
Classifier: Programming Language :: Python
Classifier: Programming Language :: Python :: 3
Classifier: Programming Language :: Python :: 3.10
Classifier: Programming Language :: Python :: 3.11
Classifier: Programming Language :: Python :: 3.12
Classifier: Topic :: Communications :: Chat
Classifier: Topic :: Internet :: WWW/HTTP
Classifier: Topic :: Software Development :: Libraries :: Python Modules
Requires-Dist: arrow (>=1.2.3,<2.0.0)
Requires-Dist: certifi
Requires-Dist: pydantic (>=2,<3)
Requires-Dist: requests (>=2.28.2,<3.0.0)
Project-URL: Repository, https://github.com/toomore/toldwords
